{
    "data": [
        {
            "author_id": "1279147787838459909",
            "id": "1381332886993965060",
            "text": "RT @calebmaupin: Giving imperialist America a \u201cwoke\u201d makeover to help sell it around the world as an alternative to Russia &amp; China and the\u2026"
        },
        {
            "author_id": "1205137992462954497",
            "id": "1381332886079479813",
            "text": "RT @hahadavid2002: @MichaelChongMP He  may get some benefits from China."
        },
        {
            "author_id": "1358847572559986689",
            "id": "1381332884489973769",
            "text": "RT @allanldsantos: Da s\u00e9rie \u201cSIL\u00caNCIO NA M\u00cdDIA BRASILEIRA\u201d: Partido Comunista Chin\u00eas multa empresa Alibaba em $2.8 BILH\u00d5ES DE D\u00d3LARES (mais\u2026"
        },
        {
            "author_id": "421527002",
            "id": "1381332884452171779",
            "text": "Today, western countries will deny global south countries vaccines.  A little after that, they'll arrest a few African leaders for human rights violations for not being able to get the vaccine.  And then, they'll say China did it."
        },
        {
            "author_id": "872053136",
            "id": "1381332884271685633",
            "text": "RT @emedranosBIS: Tren Maya, Tren suburbano Toluca-CDMX, 2 Bocas , Sta. Luc\u00eda y 6 Refiner\u00edas remodeladas (con un 79% de avance) Corredor de\u2026"
        },
        {
            "author_id": "862777635511947265",
            "id": "1381332883428810761",
            "text": "LPMQLORP.  LA VACUNA CHINA NO SIRVE.  ESO NOS DI\u00d3 EL IMPRESENTABLE DE KICILO. QUE DAMIER SE HACE?  CU\u00c1NDO SE VAN?"
        },
        {
            "author_id": "957975556326338560",
            "id": "1381332882195615748",
            "text": "RT @HypatiaHurtado: Soy profesora de Ciencias con dos Maestr\u00edas, en la universidad Nacional y en Espa\u00f1a, curso un Doctorado en Educaci\u00f3n ci\u2026"
        },
        {
            "author_id": "1240776679343226880",
            "id": "1381332881860091914",
            "text": "@china_verso oi"
        },
        {
            "author_id": "1056867320629522432",
            "id": "1381332880597647362",
            "text": "RT @secretsunset2: The fishermen on the River Li on the sunrise, China.\ud83d\udc9c https://t.co/yyYe1FZRx7"
        },
        {
            "author_id": "1107682606454394885",
            "id": "1381332879163150336",
            "text": "RT @Yaqiu: I remember Carl Schmitt was getting popular in my college years, but at the time liberalism was also very popular. Then the CCP\u2026"
        },
        {
            "author_id": "604753796",
            "id": "1381332878601125896",
            "text": "RT @pauli_mma: Yall hating on Rose. But Im Lithuanian as well. I know what she means. My parents/grandparents went through hell during year\u2026"
        },
        {
            "author_id": "1377971376867381249",
            "id": "1381332876965347328",
            "text": "Rose namajunas has dug herself a massive grave now she said all of that shit on Communism with China when talking about Weili. That was just not needed in the slightest."
        },
        {
            "author_id": "1337480038627864577",
            "id": "1381332874465533960",
            "text": "RT @mavica7: El contrato con Sinopharm venci\u00f3 hace 10 d\u00edas y todav\u00eda faltan 2 millones de dosis:La empresa china apenas entreg\u00f3 1 de los 3\u2026"
        },
        {
            "author_id": "4157864423",
            "id": "1381332874431971328",
            "text": "RT @CER_IanBond: The Commission saw this coming, warned Montenegro that this was what would happen and is now being asked to bail Montenegr\u2026"
        },
        {
            "author_id": "1302308441852129281",
            "id": "1381332872846577668",
            "text": "RT @leehaechan_IDN: 210410 INFO\ud83c\udf3b \nAiMan China Index\n\nplatform analisis nilai komersial selebriti paling terkenal di Tiongkok, ini hasil ana\u2026"
        },
        {
            "author_id": "1205137992462954497",
            "id": "1381332872531873793",
            "text": "RT @John68993893: @MichaelChongMP Thank you and you are right. It's been China's ambitions to take over the domination of tge world by the\u2026"
        },
        {
            "author_id": "1168335429017509888",
            "id": "1381332871336583179",
            "text": "RT @miguelm_barrios: Efectividad de la vacuna china dicen que es del 50%, pero esto es s\u00f3lo para evitar enfermedad leve. Evita en un 100% l\u2026"
        },
        {
            "author_id": "1967288077",
            "id": "1381332868379549696",
            "text": "RT @PM_Thornton: AP: US-#Philippines officials discuss concerns over #China\u2019s ships \nAustin and Lorenzana discussed the situation in the #S\u2026"
        },
        {
            "author_id": "1196222686860652547",
            "id": "1381332866492198915",
            "text": "RT @NapDragonPH: China threatens PH fisherman on PH seas, US wants to defend PH, \nPH will be a warzone for testing new weapons \ud83d\ude23\ud83d\udc80\ud83d\ude31\n#fuckChi\u2026"
        },
        {
            "author_id": "919831101228666881",
            "id": "1381332865594630146",
            "text": "@oforheavens @AmirAminiMD @PearlJolly with China"
        },
        {
            "author_id": "812003916120399872",
            "id": "1381332865422622731",
            "text": "RT @selinawangtv: I wrote this story about being a perpetual foreigner\u2013not just in my home America, but in China too\nI fear racism will wor\u2026"
        },
        {
            "author_id": "54097817",
            "id": "1381332861194809350",
            "text": "RT @Frospigliosi: China admite que sus vacunas contra el COVID tienen una efectividad baja \u2066@ErnesBustamante\u2069 ten\u00eda raz\u00f3n, son las m\u00e1s cara\u2026"
        },
        {
            "author_id": "1036621185683992577",
            "id": "1381332860901195779",
            "text": "RT @turdiogli: We launched yesterday our 2nd campaign. You are welcome to join us with #NoBeijing2022 to demand boycott #Olympic Winter Gam\u2026"
        },
        {
            "author_id": "1284542280850763776",
            "id": "1381332859185590275",
            "text": "RT @benedictrogers: How dare the Chinese Communist Party's goons in #HongKong try to tell other countries who we can &amp; can't welcome, or tr\u2026"
        },
        {
            "author_id": "1179042069765087236",
            "id": "1381332857663131658",
            "text": "RT @allanldsantos: Da s\u00e9rie \u201cSIL\u00caNCIO NA M\u00cdDIA BRASILEIRA\u201d: Partido Comunista Chin\u00eas multa empresa Alibaba em $2.8 BILH\u00d5ES DE D\u00d3LARES (mais\u2026"
        },
        {
            "author_id": "974730790071422979",
            "id": "1381332857524740096",
            "text": "RT @Bytom_Official: As one of the earliest #Blockchain #experts in China, Chang Jia, Founder of @Bytom_Official  and @btcinchina gives his\u2026"
        },
        {
            "author_id": "338899489",
            "id": "1381332856752857088",
            "text": "DDSlandia in support of the traitor in the palace would always calim that resisting China would mean war and futile, hence, befriending or \"appease China\" diplomacy is more effective. So far, we've lost more grounds and water with this policy.\n\n1/2"
        },
        {
            "author_id": "1163086007878766592",
            "id": "1381332856723619847",
            "text": "RT @BroodStenen: Een hele uitzending gebaseerd op een boek #scheefgroei lekker hoor! What's next? Da's Kapital? Ik hoop dat ze ook de invlo\u2026"
        },
        {
            "author_id": "322043658",
            "id": "1381332856203579392",
            "text": "Alibaba and Ant Group founder Jack Ma has lost the title of China\u2019s richest man, a list published on Tuesday showed, as his peers prospered while his empire was put under heavy scrutiny by Chinese regulators.\n\nhttps://t.co/G0UigRZF6p"
        },
        {
            "author_id": "1261113215783596032",
            "id": "1381332853171101701",
            "text": "RT @Littleb29872980: Read the Law of War \nOn these numbers # posted \nThey connect EVERYTHING from the pandemic to China to the Law Of War c\u2026"
        },
        {
            "author_id": "954836156",
            "id": "1381332851833122826",
            "text": "RT @Tom_Fowdy: \"Chinese products are low quality, cheap and dangerous\"\n\nSays the person tweeting from an iPhone as he sits on a China made\u2026"
        },
        {
            "author_id": "1114325359003164672",
            "id": "1381332850881007616",
            "text": "RT @allanldsantos: Da s\u00e9rie \u201cSIL\u00caNCIO NA M\u00cdDIA BRASILEIRA\u201d: Partido Comunista Chin\u00eas multa empresa Alibaba em $2.8 BILH\u00d5ES DE D\u00d3LARES (mais\u2026"
        },
        {
            "author_id": "1296068293212557312",
            "id": "1381332845113700353",
            "text": "RT @MalkiatCol: On China attitude on de escalation on LAC"
        },
        {
            "author_id": "1036621185683992577",
            "id": "1381332841536032768",
            "text": "RT @MeetThePress: Full @SecBlinken Interview: \"We stand resolutely against\" genocide in China\n\nIn an exclusive interview with Meet the Pres\u2026"
        },
        {
            "author_id": "1123579551282552832",
            "id": "1381332838562287617",
            "text": "RT @friedmanntomas: Dice el cient\u00edfico chino:Covid-19\u2028\u00ab\u00a0Fue un completo malentendido\u201d: Jefe de agencia china para el control de las enferme\u2026"
        },
        {
            "author_id": "67001515",
            "id": "1381332837354311682",
            "text": "RT @HDoumergue: Weili: Is born in China\n\nRose: https://t.co/jnW6uIdJkU"
        },
        {
            "author_id": "1168955445580615680",
            "id": "1381332836553228293",
            "text": "RT @chitreano100: Voy a dejar \u00e9sto aqu\u00ed y hecho un par de pasos atr\u00e1s\n\nChina admiti\u00f3 que la eficacia de sus vacunas contra el Covid-19 no e\u2026"
        },
        {
            "author_id": "1358800869035245568",
            "id": "1381332836213534721",
            "text": "RT @anaderodriguez_: La vicepresidenta ejecutiva de la Rep\u00fablica, @drodriven2, se\u00f1al\u00f3 que, adem\u00e1s del Covax, Venezuela estima vacunar a 70%\u2026"
        },
        {
            "author_id": "30701862",
            "id": "1381332835542265857",
            "text": "Philippines, US to start military drills amid South China Sea tensions\n\nhttps://t.co/VBiYlXZ26K"
        },
        {
            "author_id": "1217687848775835648",
            "id": "1381332832728059906",
            "text": "@DerrickKaana China China nze mbatya"
        },
        {
            "author_id": "321523173",
            "id": "1381332832174419974",
            "text": "RT @dezoito22: China admite baixa efic\u00e1cia da Coronavac https://t.co/pbw6AuarLx"
        },
        {
            "author_id": "195099971",
            "id": "1381332831918505992",
            "text": "@rvdz1908 Hier ook koop liever origineel. Nou zie je het verschil niet vanuit china hoor."
        },
        {
            "author_id": "1354235332783435778",
            "id": "1381332829628461056",
            "text": "RT @santosjorgeh: Investigadores en Brasil han determinado que  la tasa de efectividad de una vacuna de Sinovac, una compa\u00f1\u00eda china, para e\u2026"
        },
        {
            "author_id": "810154008274833408",
            "id": "1381332829569642496",
            "text": "RT @allanldsantos: Da s\u00e9rie \u201cSIL\u00caNCIO NA M\u00cdDIA BRASILEIRA\u201d: Partido Comunista Chin\u00eas multa empresa Alibaba em $2.8 BILH\u00d5ES DE D\u00d3LARES (mais\u2026"
        },
        {
            "author_id": "1179756451910189056",
            "id": "1381332827510214657",
            "text": "RT @BossTemlen: Master plan!\nWikiLeaks: China Berencana Sekulerkan Muslim RI\nhttps://t.co/RcfIFHo6gr"
        },
        {
            "author_id": "1286292159444983808",
            "id": "1381332826176520192",
            "text": "RT @Russ_Warrior: Western elites' strategy re. #Russia/#China:\n1_ \"Bad Russians/Chinese committed this horrible thing\" (Aggression, poisoni\u2026"
        },
        {
            "author_id": "780903908159922177",
            "id": "1381332826046484487",
            "text": "RT @CarvalhoPitanga: A China admitiu publicamente, pela primeira vez, que est\u00e1 preocupada com a baixa efic\u00e1cia de suas vacinas contra a Cov\u2026"
        },
        {
            "author_id": "1194743720345817088",
            "id": "1381332821256593412",
            "text": "RT @cbofillr: Pol\u00e9mica sobre eficacia de Sinovac: 10 cosas que hay que saber sobre la vacuna china https://t.co/InJk1TQCi7"
        },
        {
            "author_id": "3091606912",
            "id": "1381332818203193348",
            "text": "RT @nypost: China admits that it COVID-19 vaccine isn't very effective: official https://t.co/QYSpRWueD0 https://t.co/jZc7YLuIfD"
        },
        {
            "author_id": "59660095",
            "id": "1381332817901191170",
            "text": "RT @mirnaschindler: \u00bfEs noticia que China reconozca que sus vacunas tienen baja efectividad al contagio? Lo es. \u00bfCambia esto el hecho que l\u2026"
        },
        {
            "author_id": "1358404878054350851",
            "id": "1381332816663879683",
            "text": "@cynaramenezes \u25aa\ufe0fN\u00e3o se esque\u00e7a da #China , segunda pot\u00eancia mundial e nosso maior parceiro comercial!\n\u25aa\ufe0f @BolsonaroSP e @ernestofaraujo agridem o gigante asi\u00e1tico on a daily basis. Com aval de Jair.\n\ud83d\udc49\ud83c\udffc Cara @EmbaixadaChina , em 01/01/2023, @LulaOficial assumir\u00e1 e isso mudar\u00e1!\ud83c\udde7\ud83c\uddf7\ud83c\udde8\ud83c\uddf3 https://t.co/0pkr9jcrh2"
        },
        {
            "author_id": "3297053364",
            "id": "1381332814461865987",
            "text": "RT @joejhehir: @Flakmagnet1 @vivamjm @QuijoteMike From the my own limited experience CE marked pharma and med device can export into China\u2026"
        },
        {
            "author_id": "1665371942",
            "id": "1381332813828476930",
            "text": "RT @TheresaAFallon: \u201cChinese vaccines \u2018don\u2019t have very high protection rates,\u2019 said the director of the China Centers for Disease Control,\u2026"
        },
        {
            "author_id": "2539098674",
            "id": "1381332812662382593",
            "text": "@docmchon Tired feeling aa rahi hai ...kya kare China ka...Covid ka...\ud83d\ude02\ud83d\ude11\ud83d\ude11"
        },
        {
            "author_id": "1245788907192582144",
            "id": "1381332810603114496",
            "text": "RT @crismartinj: \u00bfQuer\u00edais 100 % de seguridad a cambio de perder parte de vuestra libertad?\nChina crea un ej\u00e9rcito de perros robots capaces\u2026"
        },
        {
            "author_id": "1669127778",
            "id": "1381332808434647043",
            "text": "@JonathanLanday China is testing the Biden administration. Who lost Hong Kong? And, in what way could China expect to govern contemporary Taiwan?"
        },
        {
            "author_id": "110471617",
            "id": "1381332808279412737",
            "text": "RT @edgardVE: Mientras tanto la poblaci\u00f3n china est\u00e1 practicamente libre de coronavirus. No es que se est\u00e9n cuidando m\u00e1s que otros. Fueron\u2026"
        },
        {
            "author_id": "291740252",
            "id": "1381332807499255809",
            "text": "@BeijingPalmer Two things I want banned from China talk: Bad \u2018Go\u2019 analogies and the French Revolution quote. Please."
        },
        {
            "author_id": "93132077",
            "id": "1381332805054050308",
            "text": "RT @Russ_Warrior: Western elites' strategy re. #Russia/#China:\n1_ \"Bad Russians/Chinese committed this horrible thing\" (Aggression, poisoni\u2026"
        },
        {
            "author_id": "979786897043218433",
            "id": "1381332802810040329",
            "text": "@ClayTravis They are the Trump VACCINES. Why are Republicans ashamed to evidence their vaccinations with documentation? Let's act like a Team against the CHINA VIRUS!"
        },
        {
            "author_id": "1197030484858961921",
            "id": "1381332802340233216",
            "text": "@TruthAbtChina and if you really wanna show something bad about china i can tell you something happend in china recently"
        },
        {
            "author_id": "1270451298375270401",
            "id": "1381332802235424774",
            "text": "Quantities of surplus men in China and India are insane (33m and 37m respectively). Absent major conflict, not sure how they could handle those threats to social stability"
        },
        {
            "author_id": "1095924103373090816",
            "id": "1381332801421725700",
            "text": "RT @alejandroo1200: Getting vaccinated DOES NOT mean you can bring out the pink Lamborghini just to race with Chyna brought the wraith to C\u2026"
        },
        {
            "author_id": "1139178902637678593",
            "id": "1381332800213807113",
            "text": "RT @SeeSallySew: Royal Crown Derby Blue Mikado Pair of Salt &amp; Pepper Shakers Oriental Scene Bone China Made in England Blue White Excellent\u2026"
        },
        {
            "author_id": "1332787335256268800",
            "id": "1381332799991513089",
            "text": "RT @nise_yoshimi: while I don't follow qiao collective myself I find the logic of \"the majority of the world's media is cartoonishly agains\u2026"
        },
        {
            "author_id": "771791833",
            "id": "1381332799186219011",
            "text": "RT @Maui_Speaks: I bet China\u2019s and Russia\u2019s Navy\u2019s  don\u2019t have masks on their National symbols. They are so laughing at us right now.\nWho\u2019s\u2026"
        },
        {
            "author_id": "1291736909681696775",
            "id": "1381332798800343042",
            "text": "\ud83d\udd95Fuck Northeast Normal University in China \ud83c\udde8\ud83c\uddf3"
        },
        {
            "author_id": "1228664929374228481",
            "id": "1381332798271713282",
            "text": "RT @ianwill: @AFP has used reverse image search to show how photos on Chinese social media are fabricated to show Hong Kong celebs supporti\u2026"
        },
        {
            "author_id": "1002344948275048449",
            "id": "1381332796405383171",
            "text": "@CortesSteve Hutchinson is almost as clueless as China Joe!"
        },
        {
            "author_id": "1380625767655034880",
            "id": "1381332794379358208",
            "text": "RT @DewiAja84194706: di morosi antara china dan janda lokal.. https://t.co/E3zU6Qm3Ev"
        },
        {
            "author_id": "1354995809780199426",
            "id": "1381332793981026309",
            "text": "@MMAjunkie If she said FUCK THE USA YOU ALL WOULD BE CHEERING HER ON .\nHEY I KNOW GO TO CHINA BYE"
        },
        {
            "author_id": "730082396129918976",
            "id": "1381332792420798483",
            "text": "RT @luisfbatista: @taniapsuv Ese maldito no ten\u00eda dignidad, lo que ten\u00eda era maldad, por eso muri\u00f3 como un perro. Al final, la supuesta sob\u2026"
        },
        {
            "author_id": "1247824238943363072",
            "id": "1381332791724478465",
            "text": "CHINA DILO https://t.co/XyvOkznhBK"
        },
        {
            "author_id": "1088449582193795079",
            "id": "1381332791200206854",
            "text": "RT @monitoreamos: China admiti\u00f3 que sus vacunas contra el Covid-19 \u201cno tienen tasas de protecci\u00f3n muy altas\u201d https://t.co/0bIFpyKKyd"
        },
        {
            "author_id": "729051914",
            "id": "1381332789941968897",
            "text": "RT @InformatePy1: OFICIAL: China Admite la baja efectividad de sus vacunas  \n\nhttps://t.co/h7mKipDcc5 https://t.co/HIqAZZdQ2g"
        },
        {
            "author_id": "83903450",
            "id": "1381332787790282752",
            "text": "RT @HypatiaHurtado: Soy profesora de Ciencias con dos Maestr\u00edas, en la universidad Nacional y en Espa\u00f1a, curso un Doctorado en Educaci\u00f3n ci\u2026"
        },
        {
            "author_id": "1066115589524082688",
            "id": "1381332787677032454",
            "text": "RT @SigaGazetaBR: China admite baixa efic\u00e1cia da Coronavac https://t.co/9hWpHsiF27"
        },
        {
            "author_id": "1251266433683795968",
            "id": "1381332787408613382",
            "text": "RT @SigaGazetaBR: China admite baixa efic\u00e1cia da Coronavac https://t.co/9hWpHsiF27"
        },
        {
            "author_id": "2623964607",
            "id": "1381332787316330501",
            "text": "RT @Viczuri: La ALIANZA tiene las PRUEBAS sobre la PLANDEMIA. El Dr. Fauci y la Fundaci\u00f3n Gates son responsables directos de mover el virus\u2026"
        },
        {
            "author_id": "994933852048187392",
            "id": "1381332787257556994",
            "text": "RT @CarnegieEndow: \ud83d\udd14 New episode of #WorldUnpacked! \n\nThis week, @LauraLMagnuson talks to @Carnegie_Europe director @RosaBalfour about Euro\u2026"
        },
        {
            "author_id": "787722493947678721",
            "id": "1381332787236573187",
            "text": "RT @anemfermu: #DomingosDeParroquia\n\nCapilla de Suzhou, Yangcheng Lake, Suzhou, China, 2011-16\nLyndon Neri &amp; Rossana Hu - Neri &amp; Hu Design\u2026"
        },
        {
            "author_id": "3244917987",
            "id": "1381332786645192706",
            "text": "Que Ayuso es una elitista lo saben aqu\u00ed y en la China. Ese anuncio va dirigida a los madrile\u00f1os que piensan que el resto de espa\u00f1oles somos un pu\u00f1ado de pueblerinos sin dientes. Al menos no se va a Vallecas a dar un mitin, eso s\u00ed."
        },
        {
            "author_id": "1326087729797455873",
            "id": "1381332785697185794",
            "text": "RT @ipo_mantra: We all know that Coronavirus was originated from Wuhan, China and after that it spread all over the world.\n\nNow 2nd wave of\u2026"
        },
        {
            "author_id": "161683954",
            "id": "1381332781406556163",
            "text": "RT @babyaetchecopar: Le rechazamos 15 millones de vacunas a Pfizer en Diciembre y ahora estamos rezando que Rusia y China nos env\u00eden vacuna\u2026"
        },
        {
            "author_id": "1187372311604858882",
            "id": "1381332780798328837",
            "text": "A Singaporean's personal experience in #Xinjiang. Did he expose the truth that China wanted the world to know, please watch and find out! https://t.co/pB4vnK5ZsJ"
        },
        {
            "author_id": "15286685",
            "id": "1381332780144070665",
            "text": "RT @HuXijin_GT: Like China, India is a populous country with arduous task of developing economy and improving people\u2019s life. It should focu\u2026"
        },
        {
            "author_id": "1462139532",
            "id": "1381332774758490112",
            "text": "New propaganda just dropped! \n\n\"Communist China does not have real orange juice at their grocery store\" https://t.co/TwMshCqDqQ https://t.co/S4oiweV4Cx"
        },
        {
            "author_id": "146632192",
            "id": "1381332774498492420",
            "text": "RT @diegosehinkman: La noticia del d\u00eda. Los f\u00e1rmacos chinos \u201cno tienen tasas de protecci\u00f3n muy altas\u201d. Lo dice... China! https://t.co/lxb2D\u2026"
        },
        {
            "author_id": "1335714225214337030",
            "id": "1381332769582747648",
            "text": "RT @eldocbarreto: Cuidado con \"Gato por Liebre\"\n\nAtentos con intenciones del r\u00e9gimen y la aprobaci\u00f3n de recursos provenientes de la recuper\u2026"
        },
        {
            "author_id": "145088604",
            "id": "1381332769465364493",
            "text": "RT @MPPEDUCACION: #Carabobo | Con gran participaci\u00f3n y confianza, el personal del @MPPEDUCACION recibe dosis de la vacuna #Sinopharm contra\u2026"
        },
        {
            "author_id": "2497531356",
            "id": "1381332767653257218",
            "text": "RT @giga128daytoy: \u0e1a\u0e19\u0e1f\u0e49\u0e32\u0e02\u0e2d\u0e07\u0e08\u0e23\u0e34\u0e07 \u0e44\u0e21\u0e48\u0e15\u0e34\u0e14\u0e1e\u0e37\u0e49\u0e19\u0e04\u0e48\u0e30 \u0e2a\u0e32\u0e22\u0e01\u0e32\u0e23\u0e1a\u0e34\u0e19 China Eastern Airline \u0e40\u0e1b\u0e34\u0e14\u0e27\u0e34\u0e14\u0e35\u0e42\u0e2d\u0e23\u0e32\u0e22\u0e01\u0e32\u0e23 our song \u0e1a\u0e19\u0e40\u0e04\u0e23\u0e37\u0e48\u0e2d\u0e07\u0e14\u0e49\u0e27\u0e22 \u0e41\u0e07\u0e07\u0e07\u0e07\u0e07 https://t.co/J\u2026"
        },
        {
            "author_id": "1199362232137781249",
            "id": "1381332766621642760",
            "text": "RT @Marcos667788: Primeros resultados del voto en el Extranjero :\n\nSeg\u00fan las actas escrutadas de los personeros y observadores\n\nKeiko Fujim\u2026"
        },
        {
            "author_id": "381573523",
            "id": "1381332764247654408",
            "text": "@horatio_mccoy @Shiramcalcerrad @Zentollo1 @doctorpensador @Eirenezurita Mira, sospechaba que la administraci\u00f3n de la vacuna China tenia que ver, pero no lo mencion\u00e9 porque no hab\u00eda le\u00eddo nada sobre el asunto. Gracias por el art\u00edculo. Hoy hab\u00eda visto en las noticias que China reconoc\u00eda que su vacuna no era tan eficaz como cre\u00edan."
        },
        {
            "author_id": "5526792",
            "id": "1381332763777859588",
            "text": "Remember when the Chinese ambassador downplayed #COVID19 and said we were wrong to shut our borders to China? Or when the WHO declined to call it a health emergency of international concern?"
        },
        {
            "author_id": "1364888972246339584",
            "id": "1381332763236782089",
            "text": "@karenwoo_aroha Visitar a Muralha da China\n[ #ASTRO_ONEonINKIGAYO || #One || #ASTRO || @offclASTRO ]"
        },
        {
            "author_id": "424614627",
            "id": "1381332758346227712",
            "text": "RT @Gestionpe: #Lo\u00daltimo | En una rara admisi\u00f3n de la debilidad de las vacunas chinas contra el coronavirus, el principal funcionario de co\u2026"
        },
        {
            "author_id": "4899050343",
            "id": "1381332757436043264",
            "text": "@von4kk @BlackCreek8 @ms_fishscale L's??\nI think not.\nBefore Ghengis China had closed itself off from everyone else.\nIt's still kinda like that even today.\n\nIt's kinda like saying Africa has all this tech because of colonization.\n\nBoth aren't true.\nThere's every chance these things would've happened anyway"
        },
        {
            "author_id": "219413888",
            "id": "1381332757238939656",
            "text": "RT @jpcbvm: Gente, en serio.\n\nLa \u00fanica noticia es que en China se pronunciaron respecto a algo que ya sab\u00edamos desde mucho antes. Aqu\u00ed, por\u2026"
        },
        {
            "author_id": "1379165683397763076",
            "id": "1381332754223280129",
            "text": "RT @MsAvaArmstrong: people are dying of a Chinese virus but it's racist to refer to it as Chinese even though it began in China.  We are li\u2026"
        },
        {
            "author_id": "724287134987890688",
            "id": "1381332751991775234",
            "text": "@BoiWonder1994 @OurHiddenHistry @thehill Blame China seems to be the new thing now. Fuck out of here."
        }
    ],
    "meta": {
        "newest_id": "1381332886993965060",
        "next_token": "b26v89c19zqg8o3fostr7hiqumqhiw6bxiqu6py16hful",
        "oldest_id": "1381332751991775234",
        "result_count": 100
    }
}